planktonator/__init__.py
planktonator/cluster.py
planktonator/holobatch.py
planktonator/metadata.py
planktonator/metadata_wip.py
planktonator/run.py
planktonator/segmentation.py
planktonator/tools.py
planktonator/version.py
planktonator/image/__init__.py
planktonator/image/apply.py
planktonator/image/contours.py
planktonator/image/filters.py
planktonator/image/io.py
planktonator/image/stats.py
planktonator/image/threshold.py
planktonator/packageB/__init__.py
planktonator/package_B/__init__.py
planktonator-0.0.5.dist-info/LICENCE
planktonator-0.0.5.dist-info/METADATA
planktonator-0.0.5.dist-info/WHEEL
planktonator-0.0.5.dist-info/top_level.txt
planktonator-0.0.5.dist-info/RECORD
